
	<title>Tutorial: Using a Filter
	
		The following adds a filter to the table based on the
		_Search_
		<code>Text</code>
		widget.
		The user can enter search pattern in this text field
		and
		data
		which fits to the entered pattern will be displayed.
	
	Create the following new class.
	
		<programlisting language="java">
			<xi:include xmlns:xi="http://www.w3.org/2001/XInclude"
				parse="text" href="../examples/filter/PersonFilter.java" />
		</programlisting>
	
	
		Add to your search text field a <code>keyListener</code>
		which updates the filter
		and
		the
		viewer. You need also to define a new
		<code>private PersonFilter
			filter;
		</code>
		field and change the
		<code>createPartControl()</code>
		method.
	
	
		<programlisting language="java">
			<xi:include xmlns:xi="http://www.w3.org/2001/XInclude"
				parse="text" href="../examples/filter/View.java" />
		</programlisting>
	
	Run the example, filtering should work.
