= Android - Tutorial
:linkcss:
:sectnums:                                                          
:experimental:
:icons:
:imagesdir: ./img
(c) 2009, 2016 vogella GmbH
Version 0.3, 06.07.2016
:docinfodir: ../
:vgwort: 

[abstract]


=== Git version control with Eclipse (EGit) - Tutorial
		<author>
			<firstname>Lars</firstname>
			<surname>Vogel</surname>
		</author>
		<copyright>
			<year>2009</year>
			<year>2010</year>
			<year>2011</year>
			<year>2012</year>
			<year>2013</year>
			<year>2014</year>
			<year>2015</year>
			<year>2016</year>
			<holder>vogella GmbH</holder>
		</copyright>
		<pubdate>18.01.2016</pubdate>
		<releaseinfo>
			Version 4.1
		</releaseinfo>

		<abstract id="abstract">
	=== Git with Eclipse (EGit)
			 This tutorial describes the usage of EGit; an Eclipse plug-in
				to
				use the distributed version control system Git.
				This tutorial is
				based on
				Eclipse 4.5 (Mars).
			
		</abstract>
	</articleinfo>
	<?dbhtml-include href="../../web/kindle/eclipse-ide.txt"?>
include::../web/advertisement/afterTableOfContent.adoc[]
	<xi:include xmlns:xi="http://www.w3.org/2001/XInclude" href="008_about.adoc[]
	<xi:include xmlns:xi="http://www.w3.org/2001/XInclude" href="010_overview.adoc[]
	<xi:include xmlns:xi="http://www.w3.org/2001/XInclude" href="016_workspace.adoc[]
	<xi:include xmlns:xi="http://www.w3.org/2001/XInclude" href="020_commandline_git.adoc[]
	<xi:include xmlns:xi="http://www.w3.org/2001/XInclude" href="100_eclipseinstallation.adoc[]
	<xi:include xmlns:xi="http://www.w3.org/2001/XInclude" href="110_configuration.adoc[]
include::../web/advertisement/inBetween01.adoc[]
	<xi:include xmlns:xi="http://www.w3.org/2001/XInclude" href="140_repositoryview.adoc[]
	<xi:include xmlns:xi="http://www.w3.org/2001/XInclude" href="142_packageexplorer.adoc[]
	<xi:include xmlns:xi="http://www.w3.org/2001/XInclude" href="144_stagingview.adoc[]
	<xi:include xmlns:xi="http://www.w3.org/2001/XInclude" href="145_commitdialog.adoc[]
	<xi:include xmlns:xi="http://www.w3.org/2001/XInclude" href="146_historyview.adoc[]
	<xi:include xmlns:xi="http://www.w3.org/2001/XInclude" href="160_multiprojects.adoc[]
	<xi:include xmlns:xi="http://www.w3.org/2001/XInclude" href="170_exercise_localrepository.adoc[]
	
	<xi:include xmlns:xi="http://www.w3.org/2001/XInclude" href="190_clone_repository.adoc[]
	<xi:include xmlns:xi="http://www.w3.org/2001/XInclude" href="192_import_project.adoc[]
	<xi:include xmlns:xi="http://www.w3.org/2001/XInclude" href="200_team_operations.adoc[]
	<xi:include xmlns:xi="http://www.w3.org/2001/XInclude" href="210_team_operations_branch.adoc[]
include::../web/advertisement/inBetween02.adoc[]
	<xi:include xmlns:xi="http://www.w3.org/2001/XInclude" href="212_team_merge.adoc[]
	<xi:include xmlns:xi="http://www.w3.org/2001/XInclude" href="240_rebase.adoc[]
	<xi:include xmlns:xi="http://www.w3.org/2001/XInclude" href="250_reset.adoc[]
	<xi:include xmlns:xi="http://www.w3.org/2001/XInclude" href="254_cherrypick.adoc[]
	<xi:include xmlns:xi="http://www.w3.org/2001/XInclude" href="260_createpatch.adoc[]
	<xi:include xmlns:xi="http://www.w3.org/2001/XInclude" href="270_annotations.adoc[]
	<xi:include xmlns:xi="http://www.w3.org/2001/XInclude" href="280_stash.adoc[]



	<xi:include xmlns:xi="http://www.w3.org/2001/XInclude" href="340_interactive_rebase.adoc[]
include::../web/advertisement/inBetween03.adoc[]
	<xi:include xmlns:xi="http://www.w3.org/2001/XInclude" href="400_github.adoc[]
	<xi:include xmlns:xi="http://www.w3.org/2001/XInclude" href="406_eclipsessh.adoc[]
	<xi:include xmlns:xi="http://www.w3.org/2001/XInclude" href="410_githubmylyn.adoc[]
	<xi:include xmlns:xi="http://www.w3.org/2001/XInclude" href="500_commitmessages.adoc[]
	<xi:include xmlns:xi="http://www.w3.org/2001/XInclude" href="800_egitsource.adoc[]

include::../support.adoc[]
include::008_resourceslocal.adoc[]
include::../copyright.adoc[]



adoc[]
